{
	"configurations" : 
	[
		{
			"directories" : 
			[
				{
					"build" : ".",
					"jsonFile" : "directory-.-Debug-f5ebdc15457944623624.json",
					"minimumCMakeVersion" : 
					{
						"string" : "3.20"
					},
					"projectIndex" : 0,
					"source" : ".",
					"targetIndexes" : 
					[
						0,
						1
					]
				}
			],
			"name" : "Debug",
			"projects" : 
			[
				{
					"directoryIndexes" : 
					[
						0
					],
					"name" : "gRPC_server",
					"targetIndexes" : 
					[
						0,
						1
					]
				}
			],
			"targets" : 
			[
				{
					"directoryIndex" : 0,
					"id" : "protolib::@6890427a1f51a3e7e1df",
					"jsonFile" : "target-protolib-Debug-b8a948ec3adf48a10672.json",
					"name" : "protolib",
					"projectIndex" : 0
				},
				{
					"directoryIndex" : 0,
					"id" : "server::@6890427a1f51a3e7e1df",
					"jsonFile" : "target-server-Debug-a9f9784925d670f158cd.json",
					"name" : "server",
					"projectIndex" : 0
				}
			]
		}
	],
	"kind" : "codemodel",
	"paths" : 
	{
		"build" : "/root/server/build",
		"source" : "/root/server"
	},
	"version" : 
	{
		"major" : 2,
		"minor" : 6
	}
}
